transformer_heads/__init__.py
transformer_heads/config.py
transformer_heads/constants.py
transformer_heads/output.py
transformer_heads/model/__init__.py
transformer_heads/model/head.py
transformer_heads/model/model.py
transformer_heads/tests/__init__.py
transformer_heads/tests/test_evaluate.py
transformer_heads/tests/test_generate.py
transformer_heads/tests/test_gradients.py
transformer_heads/tests/test_inference_speed.py
transformer_heads/tests/test_lm_head_consistency.py
transformer_heads/tests/test_load_model.py
transformer_heads/tests/test_loss_compute.py
transformer_heads/tests/test_unsloth_issues.py
transformer_heads/util/__init__.py
transformer_heads/util/custom_loss.py
transformer_heads/util/evaluate.py
transformer_heads/util/helpers.py
transformer_heads/util/load_model.py
transformer_heads/util/load_tokenizer.py
transformer_heads/util/model.py
transformer_heads/util/prepare_model.py
transformer_heads-0.2.2.dist-info/METADATA
transformer_heads-0.2.2.dist-info/WHEEL
transformer_heads-0.2.2.dist-info/licenses/LICENSE
transformer_heads-0.2.2.dist-info/RECORD
