Metadata-Version: 2.4
Name: transformer_heads
Version: 0.2.2
Summary: Attach custom heads to transformer models.
Author-email: Yannik Keller <yannik@kelnet.de>
License: MIT License
License-File: LICENSE
Keywords: Linear Probe,Qlora,Transformer
Requires-Python: >=3.10
Requires-Dist: bitsandbytes
Requires-Dist: datasets
Requires-Dist: fire
Requires-Dist: pandas
Requires-Dist: peft
Requires-Dist: torch
Requires-Dist: tqdm
Requires-Dist: transformers
